dc_client/__init__.py
dc_client/base.py
dc_client/client.py
dc_client/client.pyi
dc_client/exceptions.py
dc_client/run_tests.py
dc_client/tests/__init__.py
dc_client/tests/base.py
alpha_dc_client-0.1.24.dist-info/METADATA
alpha_dc_client-0.1.24.dist-info/WHEEL
alpha_dc_client-0.1.24.dist-info/RECORD
