Metadata-Version: 2.4
Name: alpha-dc-client
Version: 0.1.24
Author-email: Hang GuangLiang <hanguangliang@alphaaidig.com>
Requires-Dist: alpha-dc-common==0.1.24
Requires-Dist: httpx
